sotaai/__init__.py
sotaai/cv/__init__.py
sotaai/cv/abstractions.py
sotaai/cv/fastai_wrapper.py
sotaai/cv/keras_wrapper.py
sotaai/cv/metadata.py
sotaai/cv/mmf_wrapper.py
sotaai/cv/mxnet_wrapper.py
sotaai/cv/pretrainedmodels_wrapper.py
sotaai/cv/tensorflow_wrapper.py
sotaai/cv/torch_wrapper.py
sotaai/cv/torchvision_wrapper.py
sotaai/cv/utils.py
sotaai/rl/__init__.py
sotaai/rl/abstractions.py
sotaai/rl/garage_wrapper.py
sotaai/rl/gym_wrapper.py
sotaai/rl/rllib_wrapper.py
sotaai/rl/stablebaselines3_wrapper.py
sotaai/rl/utils.py
sotaai-0.0.9.dist-info/LICENSE
sotaai-0.0.9.dist-info/METADATA
sotaai-0.0.9.dist-info/WHEEL
sotaai-0.0.9.dist-info/top_level.txt
sotaai-0.0.9.dist-info/RECORD
