Metadata-Version: 2.1
Name: sotaai
Version: 0.0.9
Summary: Stateoftheart AI Official Library
Home-page: https://github.com/stateoftheartai/sotaai
Author: Stateoftheart AI PBC
Author-email: admin@stateoftheart.ai
License: UNKNOWN
Platform: UNKNOWN
Requires-Python: >=3,<=3.8.0
Requires-Dist: scikit-image
Provides-Extra: cv
Requires-Dist: tensorflow ; extra == 'cv'
Requires-Dist: tensorflow-datasets ; extra == 'cv'
Requires-Dist: torchvision ; extra == 'cv'
Requires-Dist: torch ; extra == 'cv'
Requires-Dist: transformers ; extra == 'cv'
Requires-Dist: scikit-image ; extra == 'cv'
Requires-Dist: opencv-python (==4.5.1.48) ; extra == 'cv'
Provides-Extra: neuro
Provides-Extra: nlp
Requires-Dist: datasets ; extra == 'nlp'
Provides-Extra: rl
Requires-Dist: gym ; extra == 'rl'
Requires-Dist: procgen ; extra == 'rl'
Requires-Dist: gym-minigrid ; extra == 'rl'
Requires-Dist: box2d ; extra == 'rl'
Requires-Dist: gym[atari] ; extra == 'rl'
Requires-Dist: garage (==2020.9.0rc1) ; extra == 'rl'
Requires-Dist: mpi4py ; extra == 'rl'
Requires-Dist: akro ; extra == 'rl'
